berserk/__init__.py
berserk/clients.py
berserk/config.py
berserk/enums.py
berserk/exceptions.py
berserk/formats.py
berserk/models.py
berserk/session.py
berserk/test_client.py
berserk/test_clients.py
berserk/utils.py
berserk_downstream-0.11.12.dist-info/AUTHORS.rst
berserk_downstream-0.11.12.dist-info/LICENSE
berserk_downstream-0.11.12.dist-info/METADATA
berserk_downstream-0.11.12.dist-info/WHEEL
berserk_downstream-0.11.12.dist-info/top_level.txt
berserk_downstream-0.11.12.dist-info/zip-safe
berserk_downstream-0.11.12.dist-info/RECORD
